bbox/__init__.py
bbox/bbox.py
bbox/transform.py
bbox/measure/__init__.py
bbox/measure/area.py
bbox/measure/iou.py
bbox_python-0.1.0.dist-info/LICENSE
bbox_python-0.1.0.dist-info/METADATA
bbox_python-0.1.0.dist-info/WHEEL
bbox_python-0.1.0.dist-info/top_level.txt
bbox_python-0.1.0.dist-info/RECORD
