Metadata-Version: 2.1
Name: bbox-python
Version: 0.1.0
Summary: A Python library for handling the 2D bounding box.
Home-page: https://github.com/Pandede/bbox
Author: Pandede
License: MIT
Download-URL: https://github.com/Pandede/bbox/archive/refs/tags/v0.1.0.tar.gz
Keywords: bbox,geometry,spatial,detection,yolo
Platform: UNKNOWN
Classifier: Development Status :: 3 - Alpha
Classifier: Intended Audience :: Developers
Classifier: Topic :: Software Development :: Libraries :: Python Modules
Classifier: License :: OSI Approved :: MIT License
Classifier: Programming Language :: Python :: 3
License-File: LICENSE
Requires-Dist: pydantic
